nerve_api/__init__.py
nerve_api/nerve_api.py
nerve_api_pkg/__init__.py
nerve_api_pkg/nerve_api.py
nerve_api-0.0.5.dist-info/.gitignore
nerve_api-0.0.5.dist-info/LICENSE
nerve_api-0.0.5.dist-info/METADATA
nerve_api-0.0.5.dist-info/WHEEL
nerve_api-0.0.5.dist-info/top_level.txt
nerve_api-0.0.5.dist-info/RECORD
